{
 "NumberOfHospitals": 1,
 "NumberOfScenarios": 200,
 "TimeHorizon": 5,
 "Scenarios": [
	{
	 "id": 0,
	 "Hospitals": [
		{
		 "id": 0,
		 "Periods": [
			{
			 "time": 1,
			 "bloodDemand": 48012
			},
			{
			 "time": 2,
			 "bloodDemand": 28616
			},
			{
			 "time": 3,
			 "bloodDemand": 14927
			},
			{
			 "time": 4,
			 "bloodDemand": 7648
			},
			{
			 "time": 5,
			 "bloodDemand": 3011
			}
		 ]
		}
	 ]
	},
	{
	 "id": 1,
	 "Hospitals": [
		{
		 "id": 0,
		 "Periods": [
			{
			 "time": 1,
			 "bloodDemand": 17466
			},
			{
			 "time": 2,
			 "bloodDemand": 15736
			},
			{
			 "time": 3,
			 "bloodDemand": 10501
			},
			{
			 "time": 4,
			 "bloodDemand": 10865
			},
			{
			 "time": 5,
			 "bloodDemand": 9220
			}
		 ]
		}
	 ]
	},
	{
	 "id": 2,
	 "Hospitals": [
		{
		 "id": 0,
		 "Periods": [
			{
			 "time": 1,
			 "bloodDemand": 33311
			},
			{
			 "time": 2,
			 "bloodDemand": 21780
			},
			{
			 "time": 3,
			 "bloodDemand": 17252
			},
			{
			 "time": 4,
			 "bloodDemand": 11847
			},
			{
			 "time": 5,
			 "bloodDemand": 7336
			}
		 ]
		}
	 ]
	},
	{
	 "id": 3,
	 "Hospitals": [
		{
		 "id": 0,
		 "Periods": [
			{
			 "time": 1,
			 "bloodDemand": 35681
			},
			{
			 "time": 2,
			 "bloodDemand": 24478
			},
			{
			 "time": 3,
			 "bloodDemand": 15915
			},
			{
			 "time": 4,
			 "bloodDemand": 10107
			},
			{
			 "time": 5,
			 "bloodDemand": 6103
			}
		 ]
		}
	 ]
	},
	{
	 "id": 4,
	 "Hospitals": [
		{
		 "id": 0,
		 "Periods": [
			{
			 "time": 1,
			 "bloodDemand": 91572
			},
			{
			 "time": 2,
			 "bloodDemand": 13102
			},
			{
			 "time": 3,
			 "bloodDemand": 816
			},
			{
			 "time": 4,
			 "bloodDemand": 432
			},
			{
			 "time": 5,
			 "bloodDemand": 122
			}
		 ]
		}
	 ]
	},
	{
	 "id": 5,
	 "Hospitals": [
		{
		 "id": 0,
		 "Periods": [
			{
			 "time": 1,
			 "bloodDemand": 82887
			},
			{
			 "time": 2,
			 "bloodDemand": 16077
			},
			{
			 "time": 3,
			 "bloodDemand": 4268
			},
			{
			 "time": 4,
			 "bloodDemand": 744
			},
			{
			 "time": 5,
			 "bloodDemand": 1535
			}
		 ]
		}
	 ]
	},
	{
	 "id": 6,
	 "Hospitals": [
		{
		 "id": 0,
		 "Periods": [
			{
			 "time": 1,
			 "bloodDemand": 27641
			},
			{
			 "time": 2,
			 "bloodDemand": 20407
			},
			{
			 "time": 3,
			 "bloodDemand": 14641
			},
			{
			 "time": 4,
			 "bloodDemand": 11081
			},
			{
			 "time": 5,
			 "bloodDemand": 7839
			}
		 ]
		}
	 ]
	},
	{
	 "id": 7,
	 "Hospitals": [
		{
		 "id": 0,
		 "Periods": [
			{
			 "time": 1,
			 "bloodDemand": 94636
			},
			{
			 "time": 2,
			 "bloodDemand": 9602
			},
			{
			 "time": 3,
			 "bloodDemand": 1438
			},
			{
			 "time": 4,
			 "bloodDemand": 337
			},
			{
			 "time": 5,
			 "bloodDemand": 23
			}
		 ]
		}
	 ]
	},
	{
	 "id": 8,
	 "Hospitals": [
		{
		 "id": 0,
		 "Periods": [
			{
			 "time": 1,
			 "bloodDemand": 49373
			},
			{
			 "time": 2,
			 "bloodDemand": 30098
			},
			{
			 "time": 3,
			 "bloodDemand": 12094
			},
			{
			 "time": 4,
			 "bloodDemand": 7732
			},
			{
			 "time": 5,
			 "bloodDemand": 3310
			}
		 ]
		}
	 ]
	},
	{
	 "id": 9,
	 "Hospitals": [
		{
		 "id": 0,
		 "Periods": [
			{
			 "time": 1,
			 "bloodDemand": 85872
			},
			{
			 "time": 2,
			 "bloodDemand": 14650
			},
			{
			 "time": 3,
			 "bloodDemand": 3540
			},
			{
			 "time": 4,
			 "bloodDemand": 1593
			},
			{
			 "time": 5,
			 "bloodDemand": 199
			}
		 ]
		}
	 ]
	},
	{
	 "id": 10,
	 "Hospitals": [
		{
		 "id": 0,
		 "Periods": [
			{
			 "time": 1,
			 "bloodDemand": 17660
			},
			{
			 "time": 2,
			 "bloodDemand": 14155
			},
			{
			 "time": 3,
			 "bloodDemand": 13210
			},
			{
			 "time": 4,
			 "bloodDemand": 10372
			},
			{
			 "time": 5,
			 "bloodDemand": 9068
			}
		 ]
		}
	 ]
	},
	{
	 "id": 11,
	 "Hospitals": [
		{
		 "id": 0,
		 "Periods": [
			{
			 "time": 1,
			 "bloodDemand": 51040
			},
			{
			 "time": 2,
			 "bloodDemand": 29511
			},
			{
			 "time": 3,
			 "bloodDemand": 10894
			},
			{
			 "time": 4,
			 "bloodDemand": 8644
			},
			{
			 "time": 5,
			 "bloodDemand": 2275
			}
		 ]
		}
	 ]
	},
	{
	 "id": 12,
	 "Hospitals": [
		{
		 "id": 0,
		 "Periods": [
			{
			 "time": 1,
			 "bloodDemand": 31202
			},
			{
			 "time": 2,
			 "bloodDemand": 26168
			},
			{
			 "time": 3,
			 "bloodDemand": 14582
			},
			{
			 "time": 4,
			 "bloodDemand": 11111
			},
			{
			 "time": 5,
			 "bloodDemand": 7294
			}
		 ]
		}
	 ]
	},
	{
	 "id": 13,
	 "Hospitals": [
		{
		 "id": 0,
		 "Periods": [
			{
			 "time": 1,
			 "bloodDemand": 87910
			},
			{
			 "time": 2,
			 "bloodDemand": 11404
			},
			{
			 "time": 3,
			 "bloodDemand": 5663
			},
			{
			 "time": 4,
			 "bloodDemand": 946
			},
			{
			 "time": 5,
			 "bloodDemand": 61
			}
		 ]
		}
	 ]
	},
	{
	 "id": 14,
	 "Hospitals": [
		{
		 "id": 0,
		 "Periods": [
			{
			 "time": 1,
			 "bloodDemand": 41415
			},
			{
			 "time": 2,
			 "bloodDemand": 23204
			},
			{
			 "time": 3,
			 "bloodDemand": 15103
			},
			{
			 "time": 4,
			 "bloodDemand": 10455
			},
			{
			 "time": 5,
			 "bloodDemand": 6701
			}
		 ]
		}
	 ]
	},
	{
	 "id": 15,
	 "Hospitals": [
		{
		 "id": 0,
		 "Periods": [
			{
			 "time": 1,
			 "bloodDemand": 76967
			},
			{
			 "time": 2,
			 "bloodDemand": 20792
			},
			{
			 "time": 3,
			 "bloodDemand": 4722
			},
			{
			 "time": 4,
			 "bloodDemand": 2736
			},
			{
			 "time": 5,
			 "bloodDemand": 593
			}
		 ]
		}
	 ]
	},
	{
	 "id": 16,
	 "Hospitals": [
		{
		 "id": 0,
		 "Periods": [
			{
			 "time": 1,
			 "bloodDemand": 17395
			},
			{
			 "time": 2,
			 "bloodDemand": 14149
			},
			{
			 "time": 3,
			 "bloodDemand": 13204
			},
			{
			 "time": 4,
			 "bloodDemand": 10148
			},
			{
			 "time": 5,
			 "bloodDemand": 8338
			}
		 ]
		}
	 ]
	},
	{
	 "id": 17,
	 "Hospitals": [
		{
		 "id": 0,
		 "Periods": [
			{
			 "time": 1,
			 "bloodDemand": 59218
			},
			{
			 "time": 2,
			 "bloodDemand": 25389
			},
			{
			 "time": 3,
			 "bloodDemand": 10778
			},
			{
			 "time": 4,
			 "bloodDemand": 5101
			},
			{
			 "time": 5,
			 "bloodDemand": 2820
			}
		 ]
		}
	 ]
	},
	{
	 "id": 18,
	 "Hospitals": [
		{
		 "id": 0,
		 "Periods": [
			{
			 "time": 1,
			 "bloodDemand": 31491
			},
			{
			 "time": 2,
			 "bloodDemand": 24007
			},
			{
			 "time": 3,
			 "bloodDemand": 15389
			},
			{
			 "time": 4,
			 "bloodDemand": 12003
			},
			{
			 "time": 5,
			 "bloodDemand": 8132
			}
		 ]
		}
	 ]
	},
	{
	 "id": 19,
	 "Hospitals": [
		{
		 "id": 0,
		 "Periods": [
			{
			 "time": 1,
			 "bloodDemand": 80998
			},
			{
			 "time": 2,
			 "bloodDemand": 19635
			},
			{
			 "time": 3,
			 "bloodDemand": 4313
			},
			{
			 "time": 4,
			 "bloodDemand": 702
			},
			{
			 "time": 5,
			 "bloodDemand": 288
			}
		 ]
		}
	 ]
	},
	{
	 "id": 20,
	 "Hospitals": [
		{
		 "id": 0,
		 "Periods": [
			{
			 "time": 1,
			 "bloodDemand": 69831
			},
			{
			 "time": 2,
			 "bloodDemand": 22534
			},
			{
			 "time": 3,
			 "bloodDemand": 6377
			},
			{
			 "time": 4,
			 "bloodDemand": 4963
			},
			{
			 "time": 5,
			 "bloodDemand": 1013
			}
		 ]
		}
	 ]
	},
	{
	 "id": 21,
	 "Hospitals": [
		{
		 "id": 0,
		 "Periods": [
			{
			 "time": 1,
			 "bloodDemand": 18157
			},
			{
			 "time": 2,
			 "bloodDemand": 15229
			},
			{
			 "time": 3,
			 "bloodDemand": 12210
			},
			{
			 "time": 4,
			 "bloodDemand": 10090
			},
			{
			 "time": 5,
			 "bloodDemand": 8591
			}
		 ]
		}
	 ]
	},
	{
	 "id": 22,
	 "Hospitals": [
		{
		 "id": 0,
		 "Periods": [
			{
			 "time": 1,
			 "bloodDemand": 51801
			},
			{
			 "time": 2,
			 "bloodDemand": 29316
			},
			{
			 "time": 3,
			 "bloodDemand": 14890
			},
			{
			 "time": 4,
			 "bloodDemand": 5194
			},
			{
			 "time": 5,
			 "bloodDemand": 2642
			}
		 ]
		}
	 ]
	},
	{
	 "id": 23,
	 "Hospitals": [
		{
		 "id": 0,
		 "Periods": [
			{
			 "time": 1,
			 "bloodDemand": 52145
			},
			{
			 "time": 2,
			 "bloodDemand": 28189
			},
			{
			 "time": 3,
			 "bloodDemand": 11474
			},
			{
			 "time": 4,
			 "bloodDemand": 5589
			},
			{
			 "time": 5,
			 "bloodDemand": 4406
			}
		 ]
		}
	 ]
	},
	{
	 "id": 24,
	 "Hospitals": [
		{
		 "id": 0,
		 "Periods": [
			{
			 "time": 1,
			 "bloodDemand": 58700
			},
			{
			 "time": 2,
			 "bloodDemand": 27355
			},
			{
			 "time": 3,
			 "bloodDemand": 12282
			},
			{
			 "time": 4,
			 "bloodDemand": 4323
			},
			{
			 "time": 5,
			 "bloodDemand": 1881
			}
		 ]
		}
	 ]
	},
	{
	 "id": 25,
	 "Hospitals": [
		{
		 "id": 0,
		 "Periods": [
			{
			 "time": 1,
			 "bloodDemand": 75327
			},
			{
			 "time": 2,
			 "bloodDemand": 22273
			},
			{
			 "time": 3,
			 "bloodDemand": 5177
			},
			{
			 "time": 4,
			 "bloodDemand": 2929
			},
			{
			 "time": 5,
			 "bloodDemand": 293
			}
		 ]
		}
	 ]
	},
	{
	 "id": 26,
	 "Hospitals": [
		{
		 "id": 0,
		 "Periods": [
			{
			 "time": 1,
			 "bloodDemand": 8927
			},
			{
			 "time": 2,
			 "bloodDemand": 8095
			},
			{
			 "time": 3,
			 "bloodDemand": 7819
			},
			{
			 "time": 4,
			 "bloodDemand": 7262
			},
			{
			 "time": 5,
			 "bloodDemand": 6649
			}
		 ]
		}
	 ]
	},
	{
	 "id": 27,
	 "Hospitals": [
		{
		 "id": 0,
		 "Periods": [
			{
			 "time": 1,
			 "bloodDemand": 85222
			},
			{
			 "time": 2,
			 "bloodDemand": 15946
			},
			{
			 "time": 3,
			 "bloodDemand": 3847
			},
			{
			 "time": 4,
			 "bloodDemand": 817
			},
			{
			 "time": 5,
			 "bloodDemand": 147
			}
		 ]
		}
	 ]
	},
	{
	 "id": 28,
	 "Hospitals": [
		{
		 "id": 0,
		 "Periods": [
			{
			 "time": 1,
			 "bloodDemand": 37788
			},
			{
			 "time": 2,
			 "bloodDemand": 20327
			},
			{
			 "time": 3,
			 "bloodDemand": 16878
			},
			{
			 "time": 4,
			 "bloodDemand": 10526
			},
			{
			 "time": 5,
			 "bloodDemand": 6434
			}
		 ]
		}
	 ]
	},
	{
	 "id": 29,
	 "Hospitals": [
		{
		 "id": 0,
		 "Periods": [
			{
			 "time": 1,
			 "bloodDemand": 61708
			},
			{
			 "time": 2,
			 "bloodDemand": 27652
			},
			{
			 "time": 3,
			 "bloodDemand": 9274
			},
			{
			 "time": 4,
			 "bloodDemand": 3339
			},
			{
			 "time": 5,
			 "bloodDemand": 2495
			}
		 ]
		}
	 ]
	},
	{
	 "id": 30,
	 "Hospitals": [
		{
		 "id": 0,
		 "Periods": [
			{
			 "time": 1,
			 "bloodDemand": 89438
			},
			{
			 "time": 2,
			 "bloodDemand": 13436
			},
			{
			 "time": 3,
			 "bloodDemand": 2781
			},
			{
			 "time": 4,
			 "bloodDemand": 307
			},
			{
			 "time": 5,
			 "bloodDemand": 65
			}
		 ]
		}
	 ]
	},
	{
	 "id": 31,
	 "Hospitals": [
		{
		 "id": 0,
		 "Periods": [
			{
			 "time": 1,
			 "bloodDemand": 34444
			},
			{
			 "time": 2,
			 "bloodDemand": 22268
			},
			{
			 "time": 3,
			 "bloodDemand": 12873
			},
			{
			 "time": 4,
			 "bloodDemand": 12837
			},
			{
			 "time": 5,
			 "bloodDemand": 8131
			}
		 ]
		}
	 ]
	},
	{
	 "id": 32,
	 "Hospitals": [
		{
		 "id": 0,
		 "Periods": [
			{
			 "time": 1,
			 "bloodDemand": 16157
			},
			{
			 "time": 2,
			 "bloodDemand": 14898
			},
			{
			 "time": 3,
			 "bloodDemand": 11751
			},
			{
			 "time": 4,
			 "bloodDemand": 10292
			},
			{
			 "time": 5,
			 "bloodDemand": 9164
			}
		 ]
		}
	 ]
	},
	{
	 "id": 33,
	 "Hospitals": [
		{
		 "id": 0,
		 "Periods": [
			{
			 "time": 1,
			 "bloodDemand": 57838
			},
			{
			 "time": 2,
			 "bloodDemand": 28832
			},
			{
			 "time": 3,
			 "bloodDemand": 11665
			},
			{
			 "time": 4,
			 "bloodDemand": 4445
			},
			{
			 "time": 5,
			 "bloodDemand": 1800
			}
		 ]
		}
	 ]
	},
	{
	 "id": 34,
	 "Hospitals": [
		{
		 "id": 0,
		 "Periods": [
			{
			 "time": 1,
			 "bloodDemand": 83486
			},
			{
			 "time": 2,
			 "bloodDemand": 18017
			},
			{
			 "time": 3,
			 "bloodDemand": 3233
			},
			{
			 "time": 4,
			 "bloodDemand": 903
			},
			{
			 "time": 5,
			 "bloodDemand": 277
			}
		 ]
		}
	 ]
	},
	{
	 "id": 35,
	 "Hospitals": [
		{
		 "id": 0,
		 "Periods": [
			{
			 "time": 1,
			 "bloodDemand": 61790
			},
			{
			 "time": 2,
			 "bloodDemand": 26460
			},
			{
			 "time": 3,
			 "bloodDemand": 9734
			},
			{
			 "time": 4,
			 "bloodDemand": 3751
			},
			{
			 "time": 5,
			 "bloodDemand": 3170
			}
		 ]
		}
	 ]
	},
	{
	 "id": 36,
	 "Hospitals": [
		{
		 "id": 0,
		 "Periods": [
			{
			 "time": 1,
			 "bloodDemand": 9544
			},
			{
			 "time": 2,
			 "bloodDemand": 7550
			},
			{
			 "time": 3,
			 "bloodDemand": 6628
			},
			{
			 "time": 4,
			 "bloodDemand": 6850
			},
			{
			 "time": 5,
			 "bloodDemand": 6500
			}
		 ]
		}
	 ]
	},
	{
	 "id": 37,
	 "Hospitals": [
		{
		 "id": 0,
		 "Periods": [
			{
			 "time": 1,
			 "bloodDemand": 9104
			},
			{
			 "time": 2,
			 "bloodDemand": 8594
			},
			{
			 "time": 3,
			 "bloodDemand": 7422
			},
			{
			 "time": 4,
			 "bloodDemand": 6050
			},
			{
			 "time": 5,
			 "bloodDemand": 6703
			}
		 ]
		}
	 ]
	},
	{
	 "id": 38,
	 "Hospitals": [
		{
		 "id": 0,
		 "Periods": [
			{
			 "time": 1,
			 "bloodDemand": 8578
			},
			{
			 "time": 2,
			 "bloodDemand": 8597
			},
			{
			 "time": 3,
			 "bloodDemand": 7293
			},
			{
			 "time": 4,
			 "bloodDemand": 7121
			},
			{
			 "time": 5,
			 "bloodDemand": 4835
			}
		 ]
		}
	 ]
	},
	{
	 "id": 39,
	 "Hospitals": [
		{
		 "id": 0,
		 "Periods": [
			{
			 "time": 1,
			 "bloodDemand": 17412
			},
			{
			 "time": 2,
			 "bloodDemand": 14540
			},
			{
			 "time": 3,
			 "bloodDemand": 12561
			},
			{
			 "time": 4,
			 "bloodDemand": 10817
			},
			{
			 "time": 5,
			 "bloodDemand": 8753
			}
		 ]
		}
	 ]
	},
	{
	 "id": 40,
	 "Hospitals": [
		{
		 "id": 0,
		 "Periods": [
			{
			 "time": 1,
			 "bloodDemand": 61846
			},
			{
			 "time": 2,
			 "bloodDemand": 24986
			},
			{
			 "time": 3,
			 "bloodDemand": 12054
			},
			{
			 "time": 4,
			 "bloodDemand": 4263
			},
			{
			 "time": 5,
			 "bloodDemand": 1730
			}
		 ]
		}
	 ]
	},
	{
	 "id": 41,
	 "Hospitals": [
		{
		 "id": 0,
		 "Periods": [
			{
			 "time": 1,
			 "bloodDemand": 81896
			},
			{
			 "time": 2,
			 "bloodDemand": 17045
			},
			{
			 "time": 3,
			 "bloodDemand": 4742
			},
			{
			 "time": 4,
			 "bloodDemand": 1302
			},
			{
			 "time": 5,
			 "bloodDemand": 672
			}
		 ]
		}
	 ]
	},
	{
	 "id": 42,
	 "Hospitals": [
		{
		 "id": 0,
		 "Periods": [
			{
			 "time": 1,
			 "bloodDemand": 24693
			},
			{
			 "time": 2,
			 "bloodDemand": 21729
			},
			{
			 "time": 3,
			 "bloodDemand": 14689
			},
			{
			 "time": 4,
			 "bloodDemand": 9313
			},
			{
			 "time": 5,
			 "bloodDemand": 7798
			}
		 ]
		}
	 ]
	},
	{
	 "id": 43,
	 "Hospitals": [
		{
		 "id": 0,
		 "Periods": [
			{
			 "time": 1,
			 "bloodDemand": 26333
			},
			{
			 "time": 2,
			 "bloodDemand": 19109
			},
			{
			 "time": 3,
			 "bloodDemand": 12517
			},
			{
			 "time": 4,
			 "bloodDemand": 12399
			},
			{
			 "time": 5,
			 "bloodDemand": 8075
			}
		 ]
		}
	 ]
	},
	{
	 "id": 44,
	 "Hospitals": [
		{
		 "id": 0,
		 "Periods": [
			{
			 "time": 1,
			 "bloodDemand": 69116
			},
			{
			 "time": 2,
			 "bloodDemand": 22881
			},
			{
			 "time": 3,
			 "bloodDemand": 7585
			},
			{
			 "time": 4,
			 "bloodDemand": 3326
			},
			{
			 "time": 5,
			 "bloodDemand": 2305
			}
		 ]
		}
	 ]
	},
	{
	 "id": 45,
	 "Hospitals": [
		{
		 "id": 0,
		 "Periods": [
			{
			 "time": 1,
			 "bloodDemand": 14883
			},
			{
			 "time": 2,
			 "bloodDemand": 13510
			},
			{
			 "time": 3,
			 "bloodDemand": 13029
			},
			{
			 "time": 4,
			 "bloodDemand": 11164
			},
			{
			 "time": 5,
			 "bloodDemand": 8776
			}
		 ]
		}
	 ]
	},
	{
	 "id": 46,
	 "Hospitals": [
		{
		 "id": 0,
		 "Periods": [
			{
			 "time": 1,
			 "bloodDemand": 41827
			},
			{
			 "time": 2,
			 "bloodDemand": 27206
			},
			{
			 "time": 3,
			 "bloodDemand": 13499
			},
			{
			 "time": 4,
			 "bloodDemand": 7888
			},
			{
			 "time": 5,
			 "bloodDemand": 6815
			}
		 ]
		}
	 ]
	},
	{
	 "id": 47,
	 "Hospitals": [
		{
		 "id": 0,
		 "Periods": [
			{
			 "time": 1,
			 "bloodDemand": 52346
			},
			{
			 "time": 2,
			 "bloodDemand": 31237
			},
			{
			 "time": 3,
			 "bloodDemand": 13261
			},
			{
			 "time": 4,
			 "bloodDemand": 4356
			},
			{
			 "time": 5,
			 "bloodDemand": 2712
			}
		 ]
		}
	 ]
	},
	{
	 "id": 48,
	 "Hospitals": [
		{
		 "id": 0,
		 "Periods": [
			{
			 "time": 1,
			 "bloodDemand": 41254
			},
			{
			 "time": 2,
			 "bloodDemand": 28468
			},
			{
			 "time": 3,
			 "bloodDemand": 15563
			},
			{
			 "time": 4,
			 "bloodDemand": 8842
			},
			{
			 "time": 5,
			 "bloodDemand": 4447
			}
		 ]
		}
	 ]
	},
	{
	 "id": 49,
	 "Hospitals": [
		{
		 "id": 0,
		 "Periods": [
			{
			 "time": 1,
			 "bloodDemand": 68640
			},
			{
			 "time": 2,
			 "bloodDemand": 21219
			},
			{
			 "time": 3,
			 "bloodDemand": 7969
			},
			{
			 "time": 4,
			 "bloodDemand": 4707
			},
			{
			 "time": 5,
			 "bloodDemand": 2473
			}
		 ]
		}
	 ]
	},
	{
	 "id": 50,
	 "Hospitals": [
		{
		 "id": 0,
		 "Periods": [
			{
			 "time": 1,
			 "bloodDemand": 52540
			},
			{
			 "time": 2,
			 "bloodDemand": 28260
			},
			{
			 "time": 3,
			 "bloodDemand": 13259
			},
			{
			 "time": 4,
			 "bloodDemand": 6208
			},
			{
			 "time": 5,
			 "bloodDemand": 2599
			}
		 ]
		}
	 ]
	},
	{
	 "id": 51,
	 "Hospitals": [
		{
		 "id": 0,
		 "Periods": [
			{
			 "time": 1,
			 "bloodDemand": 18193
			},
			{
			 "time": 2,
			 "bloodDemand": 13627
			},
			{
			 "time": 3,
			 "bloodDemand": 12051
			},
			{
			 "time": 4,
			 "bloodDemand": 10507
			},
			{
			 "time": 5,
			 "bloodDemand": 9172
			}
		 ]
		}
	 ]
	},
	{
	 "id": 52,
	 "Hospitals": [
		{
		 "id": 0,
		 "Periods": [
			{
			 "time": 1,
			 "bloodDemand": 67189
			},
			{
			 "time": 2,
			 "bloodDemand": 25067
			},
			{
			 "time": 3,
			 "bloodDemand": 9371
			},
			{
			 "time": 4,
			 "bloodDemand": 3065
			},
			{
			 "time": 5,
			 "bloodDemand": 724
			}
		 ]
		}
	 ]
	},
	{
	 "id": 53,
	 "Hospitals": [
		{
		 "id": 0,
		 "Periods": [
			{
			 "time": 1,
			 "bloodDemand": 9522
			},
			{
			 "time": 2,
			 "bloodDemand": 7535
			},
			{
			 "time": 3,
			 "bloodDemand": 7781
			},
			{
			 "time": 4,
			 "bloodDemand": 7157
			},
			{
			 "time": 5,
			 "bloodDemand": 5604
			}
		 ]
		}
	 ]
	},
	{
	 "id": 54,
	 "Hospitals": [
		{
		 "id": 0,
		 "Periods": [
			{
			 "time": 1,
			 "bloodDemand": 27345
			},
			{
			 "time": 2,
			 "bloodDemand": 18753
			},
			{
			 "time": 3,
			 "bloodDemand": 15267
			},
			{
			 "time": 4,
			 "bloodDemand": 10806
			},
			{
			 "time": 5,
			 "bloodDemand": 8698
			}
		 ]
		}
	 ]
	},
	{
	 "id": 55,
	 "Hospitals": [
		{
		 "id": 0,
		 "Periods": [
			{
			 "time": 1,
			 "bloodDemand": 33749
			},
			{
			 "time": 2,
			 "bloodDemand": 23362
			},
			{
			 "time": 3,
			 "bloodDemand": 14135
			},
			{
			 "time": 4,
			 "bloodDemand": 12155
			},
			{
			 "time": 5,
			 "bloodDemand": 6688
			}
		 ]
		}
	 ]
	},
	{
	 "id": 56,
	 "Hospitals": [
		{
		 "id": 0,
		 "Periods": [
			{
			 "time": 1,
			 "bloodDemand": 8211
			},
			{
			 "time": 2,
			 "bloodDemand": 7146
			},
			{
			 "time": 3,
			 "bloodDemand": 7403
			},
			{
			 "time": 4,
			 "bloodDemand": 7230
			},
			{
			 "time": 5,
			 "bloodDemand": 6740
			}
		 ]
		}
	 ]
	},
	{
	 "id": 57,
	 "Hospitals": [
		{
		 "id": 0,
		 "Periods": [
			{
			 "time": 1,
			 "bloodDemand": 77638
			},
			{
			 "time": 2,
			 "bloodDemand": 22303
			},
			{
			 "time": 3,
			 "bloodDemand": 4144
			},
			{
			 "time": 4,
			 "bloodDemand": 1665
			},
			{
			 "time": 5,
			 "bloodDemand": 118
			}
		 ]
		}
	 ]
	},
	{
	 "id": 58,
	 "Hospitals": [
		{
		 "id": 0,
		 "Periods": [
			{
			 "time": 1,
			 "bloodDemand": 80067
			},
			{
			 "time": 2,
			 "bloodDemand": 15775
			},
			{
			 "time": 3,
			 "bloodDemand": 7175
			},
			{
			 "time": 4,
			 "bloodDemand": 1940
			},
			{
			 "time": 5,
			 "bloodDemand": 500
			}
		 ]
		}
	 ]
	},
	{
	 "id": 59,
	 "Hospitals": [
		{
		 "id": 0,
		 "Periods": [
			{
			 "time": 1,
			 "bloodDemand": 61307
			},
			{
			 "time": 2,
			 "bloodDemand": 30496
			},
			{
			 "time": 3,
			 "bloodDemand": 7477
			},
			{
			 "time": 4,
			 "bloodDemand": 3303
			},
			{
			 "time": 5,
			 "bloodDemand": 2372
			}
		 ]
		}
	 ]
	},
	{
	 "id": 60,
	 "Hospitals": [
		{
		 "id": 0,
		 "Periods": [
			{
			 "time": 1,
			 "bloodDemand": 80890
			},
			{
			 "time": 2,
			 "bloodDemand": 17270
			},
			{
			 "time": 3,
			 "bloodDemand": 4115
			},
			{
			 "time": 4,
			 "bloodDemand": 3223
			},
			{
			 "time": 5,
			 "bloodDemand": 381
			}
		 ]
		}
	 ]
	},
	{
	 "id": 61,
	 "Hospitals": [
		{
		 "id": 0,
		 "Periods": [
			{
			 "time": 1,
			 "bloodDemand": 16123
			},
			{
			 "time": 2,
			 "bloodDemand": 15953
			},
			{
			 "time": 3,
			 "bloodDemand": 12991
			},
			{
			 "time": 4,
			 "bloodDemand": 10634
			},
			{
			 "time": 5,
			 "bloodDemand": 8657
			}
		 ]
		}
	 ]
	},
	{
	 "id": 62,
	 "Hospitals": [
		{
		 "id": 0,
		 "Periods": [
			{
			 "time": 1,
			 "bloodDemand": 57300
			},
			{
			 "time": 2,
			 "bloodDemand": 25874
			},
			{
			 "time": 3,
			 "bloodDemand": 9746
			},
			{
			 "time": 4,
			 "bloodDemand": 6045
			},
			{
			 "time": 5,
			 "bloodDemand": 3468
			}
		 ]
		}
	 ]
	},
	{
	 "id": 63,
	 "Hospitals": [
		{
		 "id": 0,
		 "Periods": [
			{
			 "time": 1,
			 "bloodDemand": 18139
			},
			{
			 "time": 2,
			 "bloodDemand": 14665
			},
			{
			 "time": 3,
			 "bloodDemand": 12482
			},
			{
			 "time": 4,
			 "bloodDemand": 9563
			},
			{
			 "time": 5,
			 "bloodDemand": 7457
			}
		 ]
		}
	 ]
	},
	{
	 "id": 64,
	 "Hospitals": [
		{
		 "id": 0,
		 "Periods": [
			{
			 "time": 1,
			 "bloodDemand": 24811
			},
			{
			 "time": 2,
			 "bloodDemand": 21957
			},
			{
			 "time": 3,
			 "bloodDemand": 15740
			},
			{
			 "time": 4,
			 "bloodDemand": 11726
			},
			{
			 "time": 5,
			 "bloodDemand": 8073
			}
		 ]
		}
	 ]
	},
	{
	 "id": 65,
	 "Hospitals": [
		{
		 "id": 0,
		 "Periods": [
			{
			 "time": 1,
			 "bloodDemand": 36600
			},
			{
			 "time": 2,
			 "bloodDemand": 23886
			},
			{
			 "time": 3,
			 "bloodDemand": 12909
			},
			{
			 "time": 4,
			 "bloodDemand": 10964
			},
			{
			 "time": 5,
			 "bloodDemand": 5538
			}
		 ]
		}
	 ]
	},
	{
	 "id": 66,
	 "Hospitals": [
		{
		 "id": 0,
		 "Periods": [
			{
			 "time": 1,
			 "bloodDemand": 75222
			},
			{
			 "time": 2,
			 "bloodDemand": 26559
			},
			{
			 "time": 3,
			 "bloodDemand": 2885
			},
			{
			 "time": 4,
			 "bloodDemand": 830
			},
			{
			 "time": 5,
			 "bloodDemand": 278
			}
		 ]
		}
	 ]
	},
	{
	 "id": 67,
	 "Hospitals": [
		{
		 "id": 0,
		 "Periods": [
			{
			 "time": 1,
			 "bloodDemand": 52008
			},
			{
			 "time": 2,
			 "bloodDemand": 26282
			},
			{
			 "time": 3,
			 "bloodDemand": 13002
			},
			{
			 "time": 4,
			 "bloodDemand": 7746
			},
			{
			 "time": 5,
			 "bloodDemand": 3013
			}
		 ]
		}
	 ]
	},
	{
	 "id": 68,
	 "Hospitals": [
		{
		 "id": 0,
		 "Periods": [
			{
			 "time": 1,
			 "bloodDemand": 17709
			},
			{
			 "time": 2,
			 "bloodDemand": 14154
			},
			{
			 "time": 3,
			 "bloodDemand": 12983
			},
			{
			 "time": 4,
			 "bloodDemand": 8993
			},
			{
			 "time": 5,
			 "bloodDemand": 9028
			}
		 ]
		}
	 ]
	},
	{
	 "id": 69,
	 "Hospitals": [
		{
		 "id": 0,
		 "Periods": [
			{
			 "time": 1,
			 "bloodDemand": 8354
			},
			{
			 "time": 2,
			 "bloodDemand": 8510
			},
			{
			 "time": 3,
			 "bloodDemand": 6630
			},
			{
			 "time": 4,
			 "bloodDemand": 7063
			},
			{
			 "time": 5,
			 "bloodDemand": 6359
			}
		 ]
		}
	 ]
	},
	{
	 "id": 70,
	 "Hospitals": [
		{
		 "id": 0,
		 "Periods": [
			{
			 "time": 1,
			 "bloodDemand": 67830
			},
			{
			 "time": 2,
			 "bloodDemand": 17919
			},
			{
			 "time": 3,
			 "bloodDemand": 13478
			},
			{
			 "time": 4,
			 "bloodDemand": 4001
			},
			{
			 "time": 5,
			 "bloodDemand": 1344
			}
		 ]
		}
	 ]
	},
	{
	 "id": 71,
	 "Hospitals": [
		{
		 "id": 0,
		 "Periods": [
			{
			 "time": 1,
			 "bloodDemand": 50569
			},
			{
			 "time": 2,
			 "bloodDemand": 29089
			},
			{
			 "time": 3,
			 "bloodDemand": 11530
			},
			{
			 "time": 4,
			 "bloodDemand": 6385
			},
			{
			 "time": 5,
			 "bloodDemand": 3168
			}
		 ]
		}
	 ]
	},
	{
	 "id": 72,
	 "Hospitals": [
		{
		 "id": 0,
		 "Periods": [
			{
			 "time": 1,
			 "bloodDemand": 93434
			},
			{
			 "time": 2,
			 "bloodDemand": 11113
			},
			{
			 "time": 3,
			 "bloodDemand": 1098
			},
			{
			 "time": 4,
			 "bloodDemand": 267
			},
			{
			 "time": 5,
			 "bloodDemand": 112
			}
		 ]
		}
	 ]
	},
	{
	 "id": 73,
	 "Hospitals": [
		{
		 "id": 0,
		 "Periods": [
			{
			 "time": 1,
			 "bloodDemand": 34408
			},
			{
			 "time": 2,
			 "bloodDemand": 21056
			},
			{
			 "time": 3,
			 "bloodDemand": 18024
			},
			{
			 "time": 4,
			 "bloodDemand": 10999
			},
			{
			 "time": 5,
			 "bloodDemand": 5894
			}
		 ]
		}
	 ]
	},
	{
	 "id": 74,
	 "Hospitals": [
		{
		 "id": 0,
		 "Periods": [
			{
			 "time": 1,
			 "bloodDemand": 73107
			},
			{
			 "time": 2,
			 "bloodDemand": 25294
			},
			{
			 "time": 3,
			 "bloodDemand": 5896
			},
			{
			 "time": 4,
			 "bloodDemand": 1225
			},
			{
			 "time": 5,
			 "bloodDemand": 394
			}
		 ]
		}
	 ]
	},
	{
	 "id": 75,
	 "Hospitals": [
		{
		 "id": 0,
		 "Periods": [
			{
			 "time": 1,
			 "bloodDemand": 76351
			},
			{
			 "time": 2,
			 "bloodDemand": 20884
			},
			{
			 "time": 3,
			 "bloodDemand": 5733
			},
			{
			 "time": 4,
			 "bloodDemand": 1637
			},
			{
			 "time": 5,
			 "bloodDemand": 1023
			}
		 ]
		}
	 ]
	},
	{
	 "id": 76,
	 "Hospitals": [
		{
		 "id": 0,
		 "Periods": [
			{
			 "time": 1,
			 "bloodDemand": 27922
			},
			{
			 "time": 2,
			 "bloodDemand": 18442
			},
			{
			 "time": 3,
			 "bloodDemand": 13518
			},
			{
			 "time": 4,
			 "bloodDemand": 11233
			},
			{
			 "time": 5,
			 "bloodDemand": 7528
			}
		 ]
		}
	 ]
	},
	{
	 "id": 77,
	 "Hospitals": [
		{
		 "id": 0,
		 "Periods": [
			{
			 "time": 1,
			 "bloodDemand": 54214
			},
			{
			 "time": 2,
			 "bloodDemand": 27007
			},
			{
			 "time": 3,
			 "bloodDemand": 10127
			},
			{
			 "time": 4,
			 "bloodDemand": 6830
			},
			{
			 "time": 5,
			 "bloodDemand": 3831
			}
		 ]
		}
	 ]
	},
	{
	 "id": 78,
	 "Hospitals": [
		{
		 "id": 0,
		 "Periods": [
			{
			 "time": 1,
			 "bloodDemand": 42454
			},
			{
			 "time": 2,
			 "bloodDemand": 26913
			},
			{
			 "time": 3,
			 "bloodDemand": 15418
			},
			{
			 "time": 4,
			 "bloodDemand": 8796
			},
			{
			 "time": 5,
			 "bloodDemand": 4671
			}
		 ]
		}
	 ]
	},
	{
	 "id": 79,
	 "Hospitals": [
		{
		 "id": 0,
		 "Periods": [
			{
			 "time": 1,
			 "bloodDemand": 16215
			},
			{
			 "time": 2,
			 "bloodDemand": 15670
			},
			{
			 "time": 3,
			 "bloodDemand": 11467
			},
			{
			 "time": 4,
			 "bloodDemand": 11020
			},
			{
			 "time": 5,
			 "bloodDemand": 9228
			}
		 ]
		}
	 ]
	},
	{
	 "id": 80,
	 "Hospitals": [
		{
		 "id": 0,
		 "Periods": [
			{
			 "time": 1,
			 "bloodDemand": 53767
			},
			{
			 "time": 2,
			 "bloodDemand": 30675
			},
			{
			 "time": 3,
			 "bloodDemand": 10190
			},
			{
			 "time": 4,
			 "bloodDemand": 7184
			},
			{
			 "time": 5,
			 "bloodDemand": 2631
			}
		 ]
		}
	 ]
	},
	{
	 "id": 81,
	 "Hospitals": [
		{
		 "id": 0,
		 "Periods": [
			{
			 "time": 1,
			 "bloodDemand": 32589
			},
			{
			 "time": 2,
			 "bloodDemand": 24410
			},
			{
			 "time": 3,
			 "bloodDemand": 16490
			},
			{
			 "time": 4,
			 "bloodDemand": 11215
			},
			{
			 "time": 5,
			 "bloodDemand": 5820
			}
		 ]
		}
	 ]
	},
	{
	 "id": 82,
	 "Hospitals": [
		{
		 "id": 0,
		 "Periods": [
			{
			 "time": 1,
			 "bloodDemand": 42437
			},
			{
			 "time": 2,
			 "bloodDemand": 25285
			},
			{
			 "time": 3,
			 "bloodDemand": 14438
			},
			{
			 "time": 4,
			 "bloodDemand": 10197
			},
			{
			 "time": 5,
			 "bloodDemand": 4734
			}
		 ]
		}
	 ]
	},
	{
	 "id": 83,
	 "Hospitals": [
		{
		 "id": 0,
		 "Periods": [
			{
			 "time": 1,
			 "bloodDemand": 28113
			},
			{
			 "time": 2,
			 "bloodDemand": 18219
			},
			{
			 "time": 3,
			 "bloodDemand": 14978
			},
			{
			 "time": 4,
			 "bloodDemand": 10767
			},
			{
			 "time": 5,
			 "bloodDemand": 8544
			}
		 ]
		}
	 ]
	},
	{
	 "id": 84,
	 "Hospitals": [
		{
		 "id": 0,
		 "Periods": [
			{
			 "time": 1,
			 "bloodDemand": 43329
			},
			{
			 "time": 2,
			 "bloodDemand": 24275
			},
			{
			 "time": 3,
			 "bloodDemand": 16335
			},
			{
			 "time": 4,
			 "bloodDemand": 9733
			},
			{
			 "time": 5,
			 "bloodDemand": 4526
			}
		 ]
		}
	 ]
	},
	{
	 "id": 85,
	 "Hospitals": [
		{
		 "id": 0,
		 "Periods": [
			{
			 "time": 1,
			 "bloodDemand": 24888
			},
			{
			 "time": 2,
			 "bloodDemand": 20342
			},
			{
			 "time": 3,
			 "bloodDemand": 16345
			},
			{
			 "time": 4,
			 "bloodDemand": 10863
			},
			{
			 "time": 5,
			 "bloodDemand": 8527
			}
		 ]
		}
	 ]
	},
	{
	 "id": 86,
	 "Hospitals": [
		{
		 "id": 0,
		 "Periods": [
			{
			 "time": 1,
			 "bloodDemand": 52213
			},
			{
			 "time": 2,
			 "bloodDemand": 28355
			},
			{
			 "time": 3,
			 "bloodDemand": 12112
			},
			{
			 "time": 4,
			 "bloodDemand": 6410
			},
			{
			 "time": 5,
			 "bloodDemand": 3150
			}
		 ]
		}
	 ]
	},
	{
	 "id": 87,
	 "Hospitals": [
		{
		 "id": 0,
		 "Periods": [
			{
			 "time": 1,
			 "bloodDemand": 31900
			},
			{
			 "time": 2,
			 "bloodDemand": 26651
			},
			{
			 "time": 3,
			 "bloodDemand": 13124
			},
			{
			 "time": 4,
			 "bloodDemand": 10871
			},
			{
			 "time": 5,
			 "bloodDemand": 6413
			}
		 ]
		}
	 ]
	},
	{
	 "id": 88,
	 "Hospitals": [
		{
		 "id": 0,
		 "Periods": [
			{
			 "time": 1,
			 "bloodDemand": 51436
			},
			{
			 "time": 2,
			 "bloodDemand": 30634
			},
			{
			 "time": 3,
			 "bloodDemand": 14304
			},
			{
			 "time": 4,
			 "bloodDemand": 4461
			},
			{
			 "time": 5,
			 "bloodDemand": 2248
			}
		 ]
		}
	 ]
	},
	{
	 "id": 89,
	 "Hospitals": [
		{
		 "id": 0,
		 "Periods": [
			{
			 "time": 1,
			 "bloodDemand": 58006
			},
			{
			 "time": 2,
			 "bloodDemand": 27470
			},
			{
			 "time": 3,
			 "bloodDemand": 10901
			},
			{
			 "time": 4,
			 "bloodDemand": 5583
			},
			{
			 "time": 5,
			 "bloodDemand": 1699
			}
		 ]
		}
	 ]
	},
	{
	 "id": 90,
	 "Hospitals": [
		{
		 "id": 0,
		 "Periods": [
			{
			 "time": 1,
			 "bloodDemand": 57932
			},
			{
			 "time": 2,
			 "bloodDemand": 24614
			},
			{
			 "time": 3,
			 "bloodDemand": 11118
			},
			{
			 "time": 4,
			 "bloodDemand": 6527
			},
			{
			 "time": 5,
			 "bloodDemand": 2674
			}
		 ]
		}
	 ]
	},
	{
	 "id": 91,
	 "Hospitals": [
		{
		 "id": 0,
		 "Periods": [
			{
			 "time": 1,
			 "bloodDemand": 40011
			},
			{
			 "time": 2,
			 "bloodDemand": 26839
			},
			{
			 "time": 3,
			 "bloodDemand": 15978
			},
			{
			 "time": 4,
			 "bloodDemand": 8852
			},
			{
			 "time": 5,
			 "bloodDemand": 5365
			}
		 ]
		}
	 ]
	},
	{
	 "id": 92,
	 "Hospitals": [
		{
		 "id": 0,
		 "Periods": [
			{
			 "time": 1,
			 "bloodDemand": 9332
			},
			{
			 "time": 2,
			 "bloodDemand": 7118
			},
			{
			 "time": 3,
			 "bloodDemand": 7693
			},
			{
			 "time": 4,
			 "bloodDemand": 7199
			},
			{
			 "time": 5,
			 "bloodDemand": 6486
			}
		 ]
		}
	 ]
	},
	{
	 "id": 93,
	 "Hospitals": [
		{
		 "id": 0,
		 "Periods": [
			{
			 "time": 1,
			 "bloodDemand": 66620
			},
			{
			 "time": 2,
			 "bloodDemand": 20857
			},
			{
			 "time": 3,
			 "bloodDemand": 10609
			},
			{
			 "time": 4,
			 "bloodDemand": 4751
			},
			{
			 "time": 5,
			 "bloodDemand": 1623
			}
		 ]
		}
	 ]
	},
	{
	 "id": 94,
	 "Hospitals": [
		{
		 "id": 0,
		 "Periods": [
			{
			 "time": 1,
			 "bloodDemand": 45608
			},
			{
			 "time": 2,
			 "bloodDemand": 25229
			},
			{
			 "time": 3,
			 "bloodDemand": 15313
			},
			{
			 "time": 4,
			 "bloodDemand": 8796
			},
			{
			 "time": 5,
			 "bloodDemand": 4729
			}
		 ]
		}
	 ]
	},
	{
	 "id": 95,
	 "Hospitals": [
		{
		 "id": 0,
		 "Periods": [
			{
			 "time": 1,
			 "bloodDemand": 47285
			},
			{
			 "time": 2,
			 "bloodDemand": 27037
			},
			{
			 "time": 3,
			 "bloodDemand": 15156
			},
			{
			 "time": 4,
			 "bloodDemand": 6064
			},
			{
			 "time": 5,
			 "bloodDemand": 5680
			}
		 ]
		}
	 ]
	},
	{
	 "id": 96,
	 "Hospitals": [
		{
		 "id": 0,
		 "Periods": [
			{
			 "time": 1,
			 "bloodDemand": 73530
			},
			{
			 "time": 2,
			 "bloodDemand": 20060
			},
			{
			 "time": 3,
			 "bloodDemand": 6049
			},
			{
			 "time": 4,
			 "bloodDemand": 4993
			},
			{
			 "time": 5,
			 "bloodDemand": 1020
			}
		 ]
		}
	 ]
	},
	{
	 "id": 97,
	 "Hospitals": [
		{
		 "id": 0,
		 "Periods": [
			{
			 "time": 1,
			 "bloodDemand": 90411
			},
			{
			 "time": 2,
			 "bloodDemand": 12424
			},
			{
			 "time": 3,
			 "bloodDemand": 2769
			},
			{
			 "time": 4,
			 "bloodDemand": 311
			},
			{
			 "time": 5,
			 "bloodDemand": 59
			}
		 ]
		}
	 ]
	},
	{
	 "id": 98,
	 "Hospitals": [
		{
		 "id": 0,
		 "Periods": [
			{
			 "time": 1,
			 "bloodDemand": 26430
			},
			{
			 "time": 2,
			 "bloodDemand": 19829
			},
			{
			 "time": 3,
			 "bloodDemand": 14090
			},
			{
			 "time": 4,
			 "bloodDemand": 10691
			},
			{
			 "time": 5,
			 "bloodDemand": 8880
			}
		 ]
		}
	 ]
	},
	{
	 "id": 99,
	 "Hospitals": [
		{
		 "id": 0,
		 "Periods": [
			{
			 "time": 1,
			 "bloodDemand": 86542
			},
			{
			 "time": 2,
			 "bloodDemand": 15744
			},
			{
			 "time": 3,
			 "bloodDemand": 3057
			},
			{
			 "time": 4,
			 "bloodDemand": 391
			},
			{
			 "time": 5,
			 "bloodDemand": 144
			}
		 ]
		}
	 ]
	},
	{
	 "id": 100,
	 "Hospitals": [
		{
		 "id": 0,
		 "Periods": [
			{
			 "time": 1,
			 "bloodDemand": 27070
			},
			{
			 "time": 2,
			 "bloodDemand": 17168
			},
			{
			 "time": 3,
			 "bloodDemand": 12899
			},
			{
			 "time": 4,
			 "bloodDemand": 13147
			},
			{
			 "time": 5,
			 "bloodDemand": 8657
			}
		 ]
		}
	 ]
	},
	{
	 "id": 101,
	 "Hospitals": [
		{
		 "id": 0,
		 "Periods": [
			{
			 "time": 1,
			 "bloodDemand": 50278
			},
			{
			 "time": 2,
			 "bloodDemand": 26165
			},
			{
			 "time": 3,
			 "bloodDemand": 15845
			},
			{
			 "time": 4,
			 "bloodDemand": 6688
			},
			{
			 "time": 5,
			 "bloodDemand": 3232
			}
		 ]
		}
	 ]
	},
	{
	 "id": 102,
	 "Hospitals": [
		{
		 "id": 0,
		 "Periods": [
			{
			 "time": 1,
			 "bloodDemand": 24147
			},
			{
			 "time": 2,
			 "bloodDemand": 15881
			},
			{
			 "time": 3,
			 "bloodDemand": 15649
			},
			{
			 "time": 4,
			 "bloodDemand": 12348
			},
			{
			 "time": 5,
			 "bloodDemand": 9784
			}
		 ]
		}
	 ]
	},
	{
	 "id": 103,
	 "Hospitals": [
		{
		 "id": 0,
		 "Periods": [
			{
			 "time": 1,
			 "bloodDemand": 17558
			},
			{
			 "time": 2,
			 "bloodDemand": 15904
			},
			{
			 "time": 3,
			 "bloodDemand": 12596
			},
			{
			 "time": 4,
			 "bloodDemand": 9894
			},
			{
			 "time": 5,
			 "bloodDemand": 8973
			}
		 ]
		}
	 ]
	},
	{
	 "id": 104,
	 "Hospitals": [
		{
		 "id": 0,
		 "Periods": [
			{
			 "time": 1,
			 "bloodDemand": 18444
			},
			{
			 "time": 2,
			 "bloodDemand": 14169
			},
			{
			 "time": 3,
			 "bloodDemand": 11518
			},
			{
			 "time": 4,
			 "bloodDemand": 9555
			},
			{
			 "time": 5,
			 "bloodDemand": 7408
			}
		 ]
		}
	 ]
	},
	{
	 "id": 105,
	 "Hospitals": [
		{
		 "id": 0,
		 "Periods": [
			{
			 "time": 1,
			 "bloodDemand": 73361
			},
			{
			 "time": 2,
			 "bloodDemand": 15775
			},
			{
			 "time": 3,
			 "bloodDemand": 8729
			},
			{
			 "time": 4,
			 "bloodDemand": 4279
			},
			{
			 "time": 5,
			 "bloodDemand": 2824
			}
		 ]
		}
	 ]
	},
	{
	 "id": 106,
	 "Hospitals": [
		{
		 "id": 0,
		 "Periods": [
			{
			 "time": 1,
			 "bloodDemand": 95381
			},
			{
			 "time": 2,
			 "bloodDemand": 7886
			},
			{
			 "time": 3,
			 "bloodDemand": 2019
			},
			{
			 "time": 4,
			 "bloodDemand": 591
			},
			{
			 "time": 5,
			 "bloodDemand": 108
			}
		 ]
		}
	 ]
	},
	{
	 "id": 107,
	 "Hospitals": [
		{
		 "id": 0,
		 "Periods": [
			{
			 "time": 1,
			 "bloodDemand": 51102
			},
			{
			 "time": 2,
			 "bloodDemand": 29170
			},
			{
			 "time": 3,
			 "bloodDemand": 11743
			},
			{
			 "time": 4,
			 "bloodDemand": 6669
			},
			{
			 "time": 5,
			 "bloodDemand": 3782
			}
		 ]
		}
	 ]
	},
	{
	 "id": 108,
	 "Hospitals": [
		{
		 "id": 0,
		 "Periods": [
			{
			 "time": 1,
			 "bloodDemand": 65264
			},
			{
			 "time": 2,
			 "bloodDemand": 33293
			},
			{
			 "time": 3,
			 "bloodDemand": 5055
			},
			{
			 "time": 4,
			 "bloodDemand": 1845
			},
			{
			 "time": 5,
			 "bloodDemand": 272
			}
		 ]
		}
	 ]
	},
	{
	 "id": 109,
	 "Hospitals": [
		{
		 "id": 0,
		 "Periods": [
			{
			 "time": 1,
			 "bloodDemand": 8440
			},
			{
			 "time": 2,
			 "bloodDemand": 8105
			},
			{
			 "time": 3,
			 "bloodDemand": 7519
			},
			{
			 "time": 4,
			 "bloodDemand": 7019
			},
			{
			 "time": 5,
			 "bloodDemand": 5973
			}
		 ]
		}
	 ]
	},
	{
	 "id": 110,
	 "Hospitals": [
		{
		 "id": 0,
		 "Periods": [
			{
			 "time": 1,
			 "bloodDemand": 38534
			},
			{
			 "time": 2,
			 "bloodDemand": 24727
			},
			{
			 "time": 3,
			 "bloodDemand": 14530
			},
			{
			 "time": 4,
			 "bloodDemand": 12102
			},
			{
			 "time": 5,
			 "bloodDemand": 6411
			}
		 ]
		}
	 ]
	},
	{
	 "id": 111,
	 "Hospitals": [
		{
		 "id": 0,
		 "Periods": [
			{
			 "time": 1,
			 "bloodDemand": 63270
			},
			{
			 "time": 2,
			 "bloodDemand": 25313
			},
			{
			 "time": 3,
			 "bloodDemand": 10426
			},
			{
			 "time": 4,
			 "bloodDemand": 4191
			},
			{
			 "time": 5,
			 "bloodDemand": 1721
			}
		 ]
		}
	 ]
	},
	{
	 "id": 112,
	 "Hospitals": [
		{
		 "id": 0,
		 "Periods": [
			{
			 "time": 1,
			 "bloodDemand": 85157
			},
			{
			 "time": 2,
			 "bloodDemand": 18705
			},
			{
			 "time": 3,
			 "bloodDemand": 1821
			},
			{
			 "time": 4,
			 "bloodDemand": 259
			},
			{
			 "time": 5,
			 "bloodDemand": 63
			}
		 ]
		}
	 ]
	},
	{
	 "id": 113,
	 "Hospitals": [
		{
		 "id": 0,
		 "Periods": [
			{
			 "time": 1,
			 "bloodDemand": 45141
			},
			{
			 "time": 2,
			 "bloodDemand": 25653
			},
			{
			 "time": 3,
			 "bloodDemand": 15423
			},
			{
			 "time": 4,
			 "bloodDemand": 6445
			},
			{
			 "time": 5,
			 "bloodDemand": 5479
			}
		 ]
		}
	 ]
	},
	{
	 "id": 114,
	 "Hospitals": [
		{
		 "id": 0,
		 "Periods": [
			{
			 "time": 1,
			 "bloodDemand": 41761
			},
			{
			 "time": 2,
			 "bloodDemand": 28576
			},
			{
			 "time": 3,
			 "bloodDemand": 13186
			},
			{
			 "time": 4,
			 "bloodDemand": 8571
			},
			{
			 "time": 5,
			 "bloodDemand": 5413
			}
		 ]
		}
	 ]
	},
	{
	 "id": 115,
	 "Hospitals": [
		{
		 "id": 0,
		 "Periods": [
			{
			 "time": 1,
			 "bloodDemand": 60061
			},
			{
			 "time": 2,
			 "bloodDemand": 28618
			},
			{
			 "time": 3,
			 "bloodDemand": 9410
			},
			{
			 "time": 4,
			 "bloodDemand": 4811
			},
			{
			 "time": 5,
			 "bloodDemand": 1813
			}
		 ]
		}
	 ]
	},
	{
	 "id": 116,
	 "Hospitals": [
		{
		 "id": 0,
		 "Periods": [
			{
			 "time": 1,
			 "bloodDemand": 26465
			},
			{
			 "time": 2,
			 "bloodDemand": 20314
			},
			{
			 "time": 3,
			 "bloodDemand": 14465
			},
			{
			 "time": 4,
			 "bloodDemand": 10265
			},
			{
			 "time": 5,
			 "bloodDemand": 9006
			}
		 ]
		}
	 ]
	},
	{
	 "id": 117,
	 "Hospitals": [
		{
		 "id": 0,
		 "Periods": [
			{
			 "time": 1,
			 "bloodDemand": 63447
			},
			{
			 "time": 2,
			 "bloodDemand": 27789
			},
			{
			 "time": 3,
			 "bloodDemand": 8829
			},
			{
			 "time": 4,
			 "bloodDemand": 3248
			},
			{
			 "time": 5,
			 "bloodDemand": 1746
			}
		 ]
		}
	 ]
	},
	{
	 "id": 118,
	 "Hospitals": [
		{
		 "id": 0,
		 "Periods": [
			{
			 "time": 1,
			 "bloodDemand": 70366
			},
			{
			 "time": 2,
			 "bloodDemand": 22547
			},
			{
			 "time": 3,
			 "bloodDemand": 9249
			},
			{
			 "time": 4,
			 "bloodDemand": 2537
			},
			{
			 "time": 5,
			 "bloodDemand": 930
			}
		 ]
		}
	 ]
	},
	{
	 "id": 119,
	 "Hospitals": [
		{
		 "id": 0,
		 "Periods": [
			{
			 "time": 1,
			 "bloodDemand": 76364
			},
			{
			 "time": 2,
			 "bloodDemand": 16636
			},
			{
			 "time": 3,
			 "bloodDemand": 8355
			},
			{
			 "time": 4,
			 "bloodDemand": 3117
			},
			{
			 "time": 5,
			 "bloodDemand": 1090
			}
		 ]
		}
	 ]
	},
	{
	 "id": 120,
	 "Hospitals": [
		{
		 "id": 0,
		 "Periods": [
			{
			 "time": 1,
			 "bloodDemand": 14564
			},
			{
			 "time": 2,
			 "bloodDemand": 15986
			},
			{
			 "time": 3,
			 "bloodDemand": 11894
			},
			{
			 "time": 4,
			 "bloodDemand": 11036
			},
			{
			 "time": 5,
			 "bloodDemand": 7139
			}
		 ]
		}
	 ]
	},
	{
	 "id": 121,
	 "Hospitals": [
		{
		 "id": 0,
		 "Periods": [
			{
			 "time": 1,
			 "bloodDemand": 53124
			},
			{
			 "time": 2,
			 "bloodDemand": 30652
			},
			{
			 "time": 3,
			 "bloodDemand": 11268
			},
			{
			 "time": 4,
			 "bloodDemand": 6902
			},
			{
			 "time": 5,
			 "bloodDemand": 2419
			}
		 ]
		}
	 ]
	},
	{
	 "id": 122,
	 "Hospitals": [
		{
		 "id": 0,
		 "Periods": [
			{
			 "time": 1,
			 "bloodDemand": 42371
			},
			{
			 "time": 2,
			 "bloodDemand": 27470
			},
			{
			 "time": 3,
			 "bloodDemand": 14077
			},
			{
			 "time": 4,
			 "bloodDemand": 9134
			},
			{
			 "time": 5,
			 "bloodDemand": 4468
			}
		 ]
		}
	 ]
	},
	{
	 "id": 123,
	 "Hospitals": [
		{
		 "id": 0,
		 "Periods": [
			{
			 "time": 1,
			 "bloodDemand": 95012
			},
			{
			 "time": 2,
			 "bloodDemand": 8664
			},
			{
			 "time": 3,
			 "bloodDemand": 1937
			},
			{
			 "time": 4,
			 "bloodDemand": 371
			},
			{
			 "time": 5,
			 "bloodDemand": 48
			}
		 ]
		}
	 ]
	},
	{
	 "id": 124,
	 "Hospitals": [
		{
		 "id": 0,
		 "Periods": [
			{
			 "time": 1,
			 "bloodDemand": 75163
			},
			{
			 "time": 2,
			 "bloodDemand": 18959
			},
			{
			 "time": 3,
			 "bloodDemand": 8445
			},
			{
			 "time": 4,
			 "bloodDemand": 2432
			},
			{
			 "time": 5,
			 "bloodDemand": 729
			}
		 ]
		}
	 ]
	},
	{
	 "id": 125,
	 "Hospitals": [
		{
		 "id": 0,
		 "Periods": [
			{
			 "time": 1,
			 "bloodDemand": 37998
			},
			{
			 "time": 2,
			 "bloodDemand": 28837
			},
			{
			 "time": 3,
			 "bloodDemand": 11606
			},
			{
			 "time": 4,
			 "bloodDemand": 11248
			},
			{
			 "time": 5,
			 "bloodDemand": 6465
			}
		 ]
		}
	 ]
	},
	{
	 "id": 126,
	 "Hospitals": [
		{
		 "id": 0,
		 "Periods": [
			{
			 "time": 1,
			 "bloodDemand": 54781
			},
			{
			 "time": 2,
			 "bloodDemand": 26296
			},
			{
			 "time": 3,
			 "bloodDemand": 14897
			},
			{
			 "time": 4,
			 "bloodDemand": 4706
			},
			{
			 "time": 5,
			 "bloodDemand": 2474
			}
		 ]
		}
	 ]
	},
	{
	 "id": 127,
	 "Hospitals": [
		{
		 "id": 0,
		 "Periods": [
			{
			 "time": 1,
			 "bloodDemand": 36805
			},
			{
			 "time": 2,
			 "bloodDemand": 24201
			},
			{
			 "time": 3,
			 "bloodDemand": 15048
			},
			{
			 "time": 4,
			 "bloodDemand": 10587
			},
			{
			 "time": 5,
			 "bloodDemand": 6250
			}
		 ]
		}
	 ]
	},
	{
	 "id": 128,
	 "Hospitals": [
		{
		 "id": 0,
		 "Periods": [
			{
			 "time": 1,
			 "bloodDemand": 92249
			},
			{
			 "time": 2,
			 "bloodDemand": 10742
			},
			{
			 "time": 3,
			 "bloodDemand": 2248
			},
			{
			 "time": 4,
			 "bloodDemand": 661
			},
			{
			 "time": 5,
			 "bloodDemand": 99
			}
		 ]
		}
	 ]
	},
	{
	 "id": 129,
	 "Hospitals": [
		{
		 "id": 0,
		 "Periods": [
			{
			 "time": 1,
			 "bloodDemand": 81868
			},
			{
			 "time": 2,
			 "bloodDemand": 18579
			},
			{
			 "time": 3,
			 "bloodDemand": 4195
			},
			{
			 "time": 4,
			 "bloodDemand": 699
			},
			{
			 "time": 5,
			 "bloodDemand": 556
			}
		 ]
		}
	 ]
	},
	{
	 "id": 130,
	 "Hospitals": [
		{
		 "id": 0,
		 "Periods": [
			{
			 "time": 1,
			 "bloodDemand": 50707
			},
			{
			 "time": 2,
			 "bloodDemand": 27728
			},
			{
			 "time": 3,
			 "bloodDemand": 17430
			},
			{
			 "time": 4,
			 "bloodDemand": 6307
			},
			{
			 "time": 5,
			 "bloodDemand": 2309
			}
		 ]
		}
	 ]
	},
	{
	 "id": 131,
	 "Hospitals": [
		{
		 "id": 0,
		 "Periods": [
			{
			 "time": 1,
			 "bloodDemand": 80914
			},
			{
			 "time": 2,
			 "bloodDemand": 20619
			},
			{
			 "time": 3,
			 "bloodDemand": 3151
			},
			{
			 "time": 4,
			 "bloodDemand": 936
			},
			{
			 "time": 5,
			 "bloodDemand": 371
			}
		 ]
		}
	 ]
	},
	{
	 "id": 132,
	 "Hospitals": [
		{
		 "id": 0,
		 "Periods": [
			{
			 "time": 1,
			 "bloodDemand": 49245
			},
			{
			 "time": 2,
			 "bloodDemand": 29557
			},
			{
			 "time": 3,
			 "bloodDemand": 13450
			},
			{
			 "time": 4,
			 "bloodDemand": 6187
			},
			{
			 "time": 5,
			 "bloodDemand": 3724
			}
		 ]
		}
	 ]
	},
	{
	 "id": 133,
	 "Hospitals": [
		{
		 "id": 0,
		 "Periods": [
			{
			 "time": 1,
			 "bloodDemand": 8600
			},
			{
			 "time": 2,
			 "bloodDemand": 7988
			},
			{
			 "time": 3,
			 "bloodDemand": 6631
			},
			{
			 "time": 4,
			 "bloodDemand": 7189
			},
			{
			 "time": 5,
			 "bloodDemand": 6198
			}
		 ]
		}
	 ]
	},
	{
	 "id": 134,
	 "Hospitals": [
		{
		 "id": 0,
		 "Periods": [
			{
			 "time": 1,
			 "bloodDemand": 17057
			},
			{
			 "time": 2,
			 "bloodDemand": 13298
			},
			{
			 "time": 3,
			 "bloodDemand": 12888
			},
			{
			 "time": 4,
			 "bloodDemand": 10308
			},
			{
			 "time": 5,
			 "bloodDemand": 8697
			}
		 ]
		}
	 ]
	},
	{
	 "id": 135,
	 "Hospitals": [
		{
		 "id": 0,
		 "Periods": [
			{
			 "time": 1,
			 "bloodDemand": 91347
			},
			{
			 "time": 2,
			 "bloodDemand": 12450
			},
			{
			 "time": 3,
			 "bloodDemand": 1971
			},
			{
			 "time": 4,
			 "bloodDemand": 259
			},
			{
			 "time": 5,
			 "bloodDemand": 15
			}
		 ]
		}
	 ]
	},
	{
	 "id": 136,
	 "Hospitals": [
		{
		 "id": 0,
		 "Periods": [
			{
			 "time": 1,
			 "bloodDemand": 85296
			},
			{
			 "time": 2,
			 "bloodDemand": 19567
			},
			{
			 "time": 3,
			 "bloodDemand": 1045
			},
			{
			 "time": 4,
			 "bloodDemand": 104
			},
			{
			 "time": 5,
			 "bloodDemand": 15
			}
		 ]
		}
	 ]
	},
	{
	 "id": 137,
	 "Hospitals": [
		{
		 "id": 0,
		 "Periods": [
			{
			 "time": 1,
			 "bloodDemand": 15429
			},
			{
			 "time": 2,
			 "bloodDemand": 16140
			},
			{
			 "time": 3,
			 "bloodDemand": 12144
			},
			{
			 "time": 4,
			 "bloodDemand": 10099
			},
			{
			 "time": 5,
			 "bloodDemand": 8465
			}
		 ]
		}
	 ]
	},
	{
	 "id": 138,
	 "Hospitals": [
		{
		 "id": 0,
		 "Periods": [
			{
			 "time": 1,
			 "bloodDemand": 59242
			},
			{
			 "time": 2,
			 "bloodDemand": 27955
			},
			{
			 "time": 3,
			 "bloodDemand": 11756
			},
			{
			 "time": 4,
			 "bloodDemand": 4088
			},
			{
			 "time": 5,
			 "bloodDemand": 1623
			}
		 ]
		}
	 ]
	},
	{
	 "id": 139,
	 "Hospitals": [
		{
		 "id": 0,
		 "Periods": [
			{
			 "time": 1,
			 "bloodDemand": 44325
			},
			{
			 "time": 2,
			 "bloodDemand": 27654
			},
			{
			 "time": 3,
			 "bloodDemand": 14900
			},
			{
			 "time": 4,
			 "bloodDemand": 7447
			},
			{
			 "time": 5,
			 "bloodDemand": 4642
			}
		 ]
		}
	 ]
	},
	{
	 "id": 140,
	 "Hospitals": [
		{
		 "id": 0,
		 "Periods": [
			{
			 "time": 1,
			 "bloodDemand": 72287
			},
			{
			 "time": 2,
			 "bloodDemand": 21362
			},
			{
			 "time": 3,
			 "bloodDemand": 7088
			},
			{
			 "time": 4,
			 "bloodDemand": 3700
			},
			{
			 "time": 5,
			 "bloodDemand": 712
			}
		 ]
		}
	 ]
	},
	{
	 "id": 141,
	 "Hospitals": [
		{
		 "id": 0,
		 "Periods": [
			{
			 "time": 1,
			 "bloodDemand": 61346
			},
			{
			 "time": 2,
			 "bloodDemand": 26727
			},
			{
			 "time": 3,
			 "bloodDemand": 9094
			},
			{
			 "time": 4,
			 "bloodDemand": 4725
			},
			{
			 "time": 5,
			 "bloodDemand": 2385
			}
		 ]
		}
	 ]
	},
	{
	 "id": 142,
	 "Hospitals": [
		{
		 "id": 0,
		 "Periods": [
			{
			 "time": 1,
			 "bloodDemand": 78270
			},
			{
			 "time": 2,
			 "bloodDemand": 19603
			},
			{
			 "time": 3,
			 "bloodDemand": 6681
			},
			{
			 "time": 4,
			 "bloodDemand": 969
			},
			{
			 "time": 5,
			 "bloodDemand": 413
			}
		 ]
		}
	 ]
	},
	{
	 "id": 143,
	 "Hospitals": [
		{
		 "id": 0,
		 "Periods": [
			{
			 "time": 1,
			 "bloodDemand": 78944
			},
			{
			 "time": 2,
			 "bloodDemand": 20530
			},
			{
			 "time": 3,
			 "bloodDemand": 3857
			},
			{
			 "time": 4,
			 "bloodDemand": 2057
			},
			{
			 "time": 5,
			 "bloodDemand": 324
			}
		 ]
		}
	 ]
	},
	{
	 "id": 144,
	 "Hospitals": [
		{
		 "id": 0,
		 "Periods": [
			{
			 "time": 1,
			 "bloodDemand": 53733
			},
			{
			 "time": 2,
			 "bloodDemand": 24326
			},
			{
			 "time": 3,
			 "bloodDemand": 12440
			},
			{
			 "time": 4,
			 "bloodDemand": 5976
			},
			{
			 "time": 5,
			 "bloodDemand": 4505
			}
		 ]
		}
	 ]
	},
	{
	 "id": 145,
	 "Hospitals": [
		{
		 "id": 0,
		 "Periods": [
			{
			 "time": 1,
			 "bloodDemand": 44334
			},
			{
			 "time": 2,
			 "bloodDemand": 25950
			},
			{
			 "time": 3,
			 "bloodDemand": 14513
			},
			{
			 "time": 4,
			 "bloodDemand": 8673
			},
			{
			 "time": 5,
			 "bloodDemand": 5143
			}
		 ]
		}
	 ]
	},
	{
	 "id": 146,
	 "Hospitals": [
		{
		 "id": 0,
		 "Periods": [
			{
			 "time": 1,
			 "bloodDemand": 42353
			},
			{
			 "time": 2,
			 "bloodDemand": 27233
			},
			{
			 "time": 3,
			 "bloodDemand": 14867
			},
			{
			 "time": 4,
			 "bloodDemand": 9354
			},
			{
			 "time": 5,
			 "bloodDemand": 5378
			}
		 ]
		}
	 ]
	},
	{
	 "id": 147,
	 "Hospitals": [
		{
		 "id": 0,
		 "Periods": [
			{
			 "time": 1,
			 "bloodDemand": 59558
			},
			{
			 "time": 2,
			 "bloodDemand": 24706
			},
			{
			 "time": 3,
			 "bloodDemand": 11873
			},
			{
			 "time": 4,
			 "bloodDemand": 3726
			},
			{
			 "time": 5,
			 "bloodDemand": 3438
			}
		 ]
		}
	 ]
	},
	{
	 "id": 148,
	 "Hospitals": [
		{
		 "id": 0,
		 "Periods": [
			{
			 "time": 1,
			 "bloodDemand": 67033
			},
			{
			 "time": 2,
			 "bloodDemand": 27814
			},
			{
			 "time": 3,
			 "bloodDemand": 6879
			},
			{
			 "time": 4,
			 "bloodDemand": 2469
			},
			{
			 "time": 5,
			 "bloodDemand": 1306
			}
		 ]
		}
	 ]
	},
	{
	 "id": 149,
	 "Hospitals": [
		{
		 "id": 0,
		 "Periods": [
			{
			 "time": 1,
			 "bloodDemand": 51291
			},
			{
			 "time": 2,
			 "bloodDemand": 31369
			},
			{
			 "time": 3,
			 "bloodDemand": 13278
			},
			{
			 "time": 4,
			 "bloodDemand": 5985
			},
			{
			 "time": 5,
			 "bloodDemand": 2081
			}
		 ]
		}
	 ]
	},
	{
	 "id": 150,
	 "Hospitals": [
		{
		 "id": 0,
		 "Periods": [
			{
			 "time": 1,
			 "bloodDemand": 23431
			},
			{
			 "time": 2,
			 "bloodDemand": 18113
			},
			{
			 "time": 3,
			 "bloodDemand": 15769
			},
			{
			 "time": 4,
			 "bloodDemand": 11752
			},
			{
			 "time": 5,
			 "bloodDemand": 9661
			}
		 ]
		}
	 ]
	},
	{
	 "id": 151,
	 "Hospitals": [
		{
		 "id": 0,
		 "Periods": [
			{
			 "time": 1,
			 "bloodDemand": 42598
			},
			{
			 "time": 2,
			 "bloodDemand": 27682
			},
			{
			 "time": 3,
			 "bloodDemand": 15195
			},
			{
			 "time": 4,
			 "bloodDemand": 8713
			},
			{
			 "time": 5,
			 "bloodDemand": 4700
			}
		 ]
		}
	 ]
	},
	{
	 "id": 152,
	 "Hospitals": [
		{
		 "id": 0,
		 "Periods": [
			{
			 "time": 1,
			 "bloodDemand": 36015
			},
			{
			 "time": 2,
			 "bloodDemand": 19856
			},
			{
			 "time": 3,
			 "bloodDemand": 17545
			},
			{
			 "time": 4,
			 "bloodDemand": 8139
			},
			{
			 "time": 5,
			 "bloodDemand": 7036
			}
		 ]
		}
	 ]
	},
	{
	 "id": 153,
	 "Hospitals": [
		{
		 "id": 0,
		 "Periods": [
			{
			 "time": 1,
			 "bloodDemand": 37494
			},
			{
			 "time": 2,
			 "bloodDemand": 27668
			},
			{
			 "time": 3,
			 "bloodDemand": 17849
			},
			{
			 "time": 4,
			 "bloodDemand": 9477
			},
			{
			 "time": 5,
			 "bloodDemand": 5686
			}
		 ]
		}
	 ]
	},
	{
	 "id": 154,
	 "Hospitals": [
		{
		 "id": 0,
		 "Periods": [
			{
			 "time": 1,
			 "bloodDemand": 53060
			},
			{
			 "time": 2,
			 "bloodDemand": 25035
			},
			{
			 "time": 3,
			 "bloodDemand": 14282
			},
			{
			 "time": 4,
			 "bloodDemand": 7261
			},
			{
			 "time": 5,
			 "bloodDemand": 3126
			}
		 ]
		}
	 ]
	},
	{
	 "id": 155,
	 "Hospitals": [
		{
		 "id": 0,
		 "Periods": [
			{
			 "time": 1,
			 "bloodDemand": 17093
			},
			{
			 "time": 2,
			 "bloodDemand": 14762
			},
			{
			 "time": 3,
			 "bloodDemand": 9756
			},
			{
			 "time": 4,
			 "bloodDemand": 10294
			},
			{
			 "time": 5,
			 "bloodDemand": 9375
			}
		 ]
		}
	 ]
	},
	{
	 "id": 156,
	 "Hospitals": [
		{
		 "id": 0,
		 "Periods": [
			{
			 "time": 1,
			 "bloodDemand": 93957
			},
			{
			 "time": 2,
			 "bloodDemand": 7574
			},
			{
			 "time": 3,
			 "bloodDemand": 3020
			},
			{
			 "time": 4,
			 "bloodDemand": 1308
			},
			{
			 "time": 5,
			 "bloodDemand": 172
			}
		 ]
		}
	 ]
	},
	{
	 "id": 157,
	 "Hospitals": [
		{
		 "id": 0,
		 "Periods": [
			{
			 "time": 1,
			 "bloodDemand": 26495
			},
			{
			 "time": 2,
			 "bloodDemand": 18675
			},
			{
			 "time": 3,
			 "bloodDemand": 13689
			},
			{
			 "time": 4,
			 "bloodDemand": 10729
			},
			{
			 "time": 5,
			 "bloodDemand": 9563
			}
		 ]
		}
	 ]
	},
	{
	 "id": 158,
	 "Hospitals": [
		{
		 "id": 0,
		 "Periods": [
			{
			 "time": 1,
			 "bloodDemand": 6992
			},
			{
			 "time": 2,
			 "bloodDemand": 8426
			},
			{
			 "time": 3,
			 "bloodDemand": 7504
			},
			{
			 "time": 4,
			 "bloodDemand": 6390
			},
			{
			 "time": 5,
			 "bloodDemand": 5502
			}
		 ]
		}
	 ]
	},
	{
	 "id": 159,
	 "Hospitals": [
		{
		 "id": 0,
		 "Periods": [
			{
			 "time": 1,
			 "bloodDemand": 29316
			},
			{
			 "time": 2,
			 "bloodDemand": 23724
			},
			{
			 "time": 3,
			 "bloodDemand": 14455
			},
			{
			 "time": 4,
			 "bloodDemand": 13291
			},
			{
			 "time": 5,
			 "bloodDemand": 8791
			}
		 ]
		}
	 ]
	},
	{
	 "id": 160,
	 "Hospitals": [
		{
		 "id": 0,
		 "Periods": [
			{
			 "time": 1,
			 "bloodDemand": 61475
			},
			{
			 "time": 2,
			 "bloodDemand": 24735
			},
			{
			 "time": 3,
			 "bloodDemand": 10570
			},
			{
			 "time": 4,
			 "bloodDemand": 5665
			},
			{
			 "time": 5,
			 "bloodDemand": 2148
			}
		 ]
		}
	 ]
	},
	{
	 "id": 161,
	 "Hospitals": [
		{
		 "id": 0,
		 "Periods": [
			{
			 "time": 1,
			 "bloodDemand": 59066
			},
			{
			 "time": 2,
			 "bloodDemand": 20980
			},
			{
			 "time": 3,
			 "bloodDemand": 15686
			},
			{
			 "time": 4,
			 "bloodDemand": 6152
			},
			{
			 "time": 5,
			 "bloodDemand": 1919
			}
		 ]
		}
	 ]
	},
	{
	 "id": 162,
	 "Hospitals": [
		{
		 "id": 0,
		 "Periods": [
			{
			 "time": 1,
			 "bloodDemand": 18923
			},
			{
			 "time": 2,
			 "bloodDemand": 14318
			},
			{
			 "time": 3,
			 "bloodDemand": 12674
			},
			{
			 "time": 4,
			 "bloodDemand": 9640
			},
			{
			 "time": 5,
			 "bloodDemand": 8021
			}
		 ]
		}
	 ]
	},
	{
	 "id": 163,
	 "Hospitals": [
		{
		 "id": 0,
		 "Periods": [
			{
			 "time": 1,
			 "bloodDemand": 83394
			},
			{
			 "time": 2,
			 "bloodDemand": 19220
			},
			{
			 "time": 3,
			 "bloodDemand": 2666
			},
			{
			 "time": 4,
			 "bloodDemand": 400
			},
			{
			 "time": 5,
			 "bloodDemand": 277
			}
		 ]
		}
	 ]
	},
	{
	 "id": 164,
	 "Hospitals": [
		{
		 "id": 0,
		 "Periods": [
			{
			 "time": 1,
			 "bloodDemand": 70014
			},
			{
			 "time": 2,
			 "bloodDemand": 24456
			},
			{
			 "time": 3,
			 "bloodDemand": 8353
			},
			{
			 "time": 4,
			 "bloodDemand": 2592
			},
			{
			 "time": 5,
			 "bloodDemand": 436
			}
		 ]
		}
	 ]
	},
	{
	 "id": 165,
	 "Hospitals": [
		{
		 "id": 0,
		 "Periods": [
			{
			 "time": 1,
			 "bloodDemand": 58884
			},
			{
			 "time": 2,
			 "bloodDemand": 26044
			},
			{
			 "time": 3,
			 "bloodDemand": 11093
			},
			{
			 "time": 4,
			 "bloodDemand": 4842
			},
			{
			 "time": 5,
			 "bloodDemand": 2706
			}
		 ]
		}
	 ]
	},
	{
	 "id": 166,
	 "Hospitals": [
		{
		 "id": 0,
		 "Periods": [
			{
			 "time": 1,
			 "bloodDemand": 47805
			},
			{
			 "time": 2,
			 "bloodDemand": 25689
			},
			{
			 "time": 3,
			 "bloodDemand": 13907
			},
			{
			 "time": 4,
			 "bloodDemand": 7285
			},
			{
			 "time": 5,
			 "bloodDemand": 4823
			}
		 ]
		}
	 ]
	},
	{
	 "id": 167,
	 "Hospitals": [
		{
		 "id": 0,
		 "Periods": [
			{
			 "time": 1,
			 "bloodDemand": 85008
			},
			{
			 "time": 2,
			 "bloodDemand": 17616
			},
			{
			 "time": 3,
			 "bloodDemand": 2396
			},
			{
			 "time": 4,
			 "bloodDemand": 660
			},
			{
			 "time": 5,
			 "bloodDemand": 228
			}
		 ]
		}
	 ]
	},
	{
	 "id": 168,
	 "Hospitals": [
		{
		 "id": 0,
		 "Periods": [
			{
			 "time": 1,
			 "bloodDemand": 80598
			},
			{
			 "time": 2,
			 "bloodDemand": 17243
			},
			{
			 "time": 3,
			 "bloodDemand": 6290
			},
			{
			 "time": 4,
			 "bloodDemand": 1208
			},
			{
			 "time": 5,
			 "bloodDemand": 407
			}
		 ]
		}
	 ]
	},
	{
	 "id": 169,
	 "Hospitals": [
		{
		 "id": 0,
		 "Periods": [
			{
			 "time": 1,
			 "bloodDemand": 34992
			},
			{
			 "time": 2,
			 "bloodDemand": 22070
			},
			{
			 "time": 3,
			 "bloodDemand": 16161
			},
			{
			 "time": 4,
			 "bloodDemand": 11491
			},
			{
			 "time": 5,
			 "bloodDemand": 7607
			}
		 ]
		}
	 ]
	},
	{
	 "id": 170,
	 "Hospitals": [
		{
		 "id": 0,
		 "Periods": [
			{
			 "time": 1,
			 "bloodDemand": 43740
			},
			{
			 "time": 2,
			 "bloodDemand": 27468
			},
			{
			 "time": 3,
			 "bloodDemand": 14577
			},
			{
			 "time": 4,
			 "bloodDemand": 8418
			},
			{
			 "time": 5,
			 "bloodDemand": 4404
			}
		 ]
		}
	 ]
	},
	{
	 "id": 171,
	 "Hospitals": [
		{
		 "id": 0,
		 "Periods": [
			{
			 "time": 1,
			 "bloodDemand": 51551
			},
			{
			 "time": 2,
			 "bloodDemand": 32821
			},
			{
			 "time": 3,
			 "bloodDemand": 11873
			},
			{
			 "time": 4,
			 "bloodDemand": 5664
			},
			{
			 "time": 5,
			 "bloodDemand": 1702
			}
		 ]
		}
	 ]
	},
	{
	 "id": 172,
	 "Hospitals": [
		{
		 "id": 0,
		 "Periods": [
			{
			 "time": 1,
			 "bloodDemand": 78796
			},
			{
			 "time": 2,
			 "bloodDemand": 20920
			},
			{
			 "time": 3,
			 "bloodDemand": 3319
			},
			{
			 "time": 4,
			 "bloodDemand": 2742
			},
			{
			 "time": 5,
			 "bloodDemand": 223
			}
		 ]
		}
	 ]
	},
	{
	 "id": 173,
	 "Hospitals": [
		{
		 "id": 0,
		 "Periods": [
			{
			 "time": 1,
			 "bloodDemand": 73454
			},
			{
			 "time": 2,
			 "bloodDemand": 21188
			},
			{
			 "time": 3,
			 "bloodDemand": 8702
			},
			{
			 "time": 4,
			 "bloodDemand": 1700
			},
			{
			 "time": 5,
			 "bloodDemand": 708
			}
		 ]
		}
	 ]
	},
	{
	 "id": 174,
	 "Hospitals": [
		{
		 "id": 0,
		 "Periods": [
			{
			 "time": 1,
			 "bloodDemand": 22324
			},
			{
			 "time": 2,
			 "bloodDemand": 22641
			},
			{
			 "time": 3,
			 "bloodDemand": 13129
			},
			{
			 "time": 4,
			 "bloodDemand": 9100
			},
			{
			 "time": 5,
			 "bloodDemand": 10418
			}
		 ]
		}
	 ]
	},
	{
	 "id": 175,
	 "Hospitals": [
		{
		 "id": 0,
		 "Periods": [
			{
			 "time": 1,
			 "bloodDemand": 37200
			},
			{
			 "time": 2,
			 "bloodDemand": 25316
			},
			{
			 "time": 3,
			 "bloodDemand": 16031
			},
			{
			 "time": 4,
			 "bloodDemand": 7112
			},
			{
			 "time": 5,
			 "bloodDemand": 7608
			}
		 ]
		}
	 ]
	},
	{
	 "id": 176,
	 "Hospitals": [
		{
		 "id": 0,
		 "Periods": [
			{
			 "time": 1,
			 "bloodDemand": 52385
			},
			{
			 "time": 2,
			 "bloodDemand": 26813
			},
			{
			 "time": 3,
			 "bloodDemand": 12221
			},
			{
			 "time": 4,
			 "bloodDemand": 7390
			},
			{
			 "time": 5,
			 "bloodDemand": 3866
			}
		 ]
		}
	 ]
	},
	{
	 "id": 177,
	 "Hospitals": [
		{
		 "id": 0,
		 "Periods": [
			{
			 "time": 1,
			 "bloodDemand": 51969
			},
			{
			 "time": 2,
			 "bloodDemand": 33180
			},
			{
			 "time": 3,
			 "bloodDemand": 9685
			},
			{
			 "time": 4,
			 "bloodDemand": 4141
			},
			{
			 "time": 5,
			 "bloodDemand": 4397
			}
		 ]
		}
	 ]
	},
	{
	 "id": 178,
	 "Hospitals": [
		{
		 "id": 0,
		 "Periods": [
			{
			 "time": 1,
			 "bloodDemand": 26697
			},
			{
			 "time": 2,
			 "bloodDemand": 20254
			},
			{
			 "time": 3,
			 "bloodDemand": 15846
			},
			{
			 "time": 4,
			 "bloodDemand": 10028
			},
			{
			 "time": 5,
			 "bloodDemand": 8691
			}
		 ]
		}
	 ]
	},
	{
	 "id": 179,
	 "Hospitals": [
		{
		 "id": 0,
		 "Periods": [
			{
			 "time": 1,
			 "bloodDemand": 27623
			},
			{
			 "time": 2,
			 "bloodDemand": 19112
			},
			{
			 "time": 3,
			 "bloodDemand": 14258
			},
			{
			 "time": 4,
			 "bloodDemand": 11358
			},
			{
			 "time": 5,
			 "bloodDemand": 8302
			}
		 ]
		}
	 ]
	},
	{
	 "id": 180,
	 "Hospitals": [
		{
		 "id": 0,
		 "Periods": [
			{
			 "time": 1,
			 "bloodDemand": 47754
			},
			{
			 "time": 2,
			 "bloodDemand": 23158
			},
			{
			 "time": 3,
			 "bloodDemand": 14726
			},
			{
			 "time": 4,
			 "bloodDemand": 9019
			},
			{
			 "time": 5,
			 "bloodDemand": 4713
			}
		 ]
		}
	 ]
	},
	{
	 "id": 181,
	 "Hospitals": [
		{
		 "id": 0,
		 "Periods": [
			{
			 "time": 1,
			 "bloodDemand": 24905
			},
			{
			 "time": 2,
			 "bloodDemand": 18115
			},
			{
			 "time": 3,
			 "bloodDemand": 15029
			},
			{
			 "time": 4,
			 "bloodDemand": 11635
			},
			{
			 "time": 5,
			 "bloodDemand": 6804
			}
		 ]
		}
	 ]
	},
	{
	 "id": 182,
	 "Hospitals": [
		{
		 "id": 0,
		 "Periods": [
			{
			 "time": 1,
			 "bloodDemand": 42911
			},
			{
			 "time": 2,
			 "bloodDemand": 24969
			},
			{
			 "time": 3,
			 "bloodDemand": 13728
			},
			{
			 "time": 4,
			 "bloodDemand": 8989
			},
			{
			 "time": 5,
			 "bloodDemand": 6047
			}
		 ]
		}
	 ]
	},
	{
	 "id": 183,
	 "Hospitals": [
		{
		 "id": 0,
		 "Periods": [
			{
			 "time": 1,
			 "bloodDemand": 18739
			},
			{
			 "time": 2,
			 "bloodDemand": 14868
			},
			{
			 "time": 3,
			 "bloodDemand": 10919
			},
			{
			 "time": 4,
			 "bloodDemand": 10582
			},
			{
			 "time": 5,
			 "bloodDemand": 9097
			}
		 ]
		}
	 ]
	},
	{
	 "id": 184,
	 "Hospitals": [
		{
		 "id": 0,
		 "Periods": [
			{
			 "time": 1,
			 "bloodDemand": 45987
			},
			{
			 "time": 2,
			 "bloodDemand": 30967
			},
			{
			 "time": 3,
			 "bloodDemand": 15094
			},
			{
			 "time": 4,
			 "bloodDemand": 5122
			},
			{
			 "time": 5,
			 "bloodDemand": 2860
			}
		 ]
		}
	 ]
	},
	{
	 "id": 185,
	 "Hospitals": [
		{
		 "id": 0,
		 "Periods": [
			{
			 "time": 1,
			 "bloodDemand": 24980
			},
			{
			 "time": 2,
			 "bloodDemand": 20439
			},
			{
			 "time": 3,
			 "bloodDemand": 16056
			},
			{
			 "time": 4,
			 "bloodDemand": 11461
			},
			{
			 "time": 5,
			 "bloodDemand": 6946
			}
		 ]
		}
	 ]
	},
	{
	 "id": 186,
	 "Hospitals": [
		{
		 "id": 0,
		 "Periods": [
			{
			 "time": 1,
			 "bloodDemand": 9145
			},
			{
			 "time": 2,
			 "bloodDemand": 6828
			},
			{
			 "time": 3,
			 "bloodDemand": 7755
			},
			{
			 "time": 4,
			 "bloodDemand": 5950
			},
			{
			 "time": 5,
			 "bloodDemand": 6527
			}
		 ]
		}
	 ]
	},
	{
	 "id": 187,
	 "Hospitals": [
		{
		 "id": 0,
		 "Periods": [
			{
			 "time": 1,
			 "bloodDemand": 42144
			},
			{
			 "time": 2,
			 "bloodDemand": 25511
			},
			{
			 "time": 3,
			 "bloodDemand": 17343
			},
			{
			 "time": 4,
			 "bloodDemand": 9432
			},
			{
			 "time": 5,
			 "bloodDemand": 5166
			}
		 ]
		}
	 ]
	},
	{
	 "id": 188,
	 "Hospitals": [
		{
		 "id": 0,
		 "Periods": [
			{
			 "time": 1,
			 "bloodDemand": 85315
			},
			{
			 "time": 2,
			 "bloodDemand": 16053
			},
			{
			 "time": 3,
			 "bloodDemand": 3368
			},
			{
			 "time": 4,
			 "bloodDemand": 1048
			},
			{
			 "time": 5,
			 "bloodDemand": 179
			}
		 ]
		}
	 ]
	},
	{
	 "id": 189,
	 "Hospitals": [
		{
		 "id": 0,
		 "Periods": [
			{
			 "time": 1,
			 "bloodDemand": 44788
			},
			{
			 "time": 2,
			 "bloodDemand": 29532
			},
			{
			 "time": 3,
			 "bloodDemand": 13649
			},
			{
			 "time": 4,
			 "bloodDemand": 6758
			},
			{
			 "time": 5,
			 "bloodDemand": 5339
			}
		 ]
		}
	 ]
	},
	{
	 "id": 190,
	 "Hospitals": [
		{
		 "id": 0,
		 "Periods": [
			{
			 "time": 1,
			 "bloodDemand": 61262
			},
			{
			 "time": 2,
			 "bloodDemand": 28057
			},
			{
			 "time": 3,
			 "bloodDemand": 8424
			},
			{
			 "time": 4,
			 "bloodDemand": 5205
			},
			{
			 "time": 5,
			 "bloodDemand": 1838
			}
		 ]
		}
	 ]
	},
	{
	 "id": 191,
	 "Hospitals": [
		{
		 "id": 0,
		 "Periods": [
			{
			 "time": 1,
			 "bloodDemand": 50119
			},
			{
			 "time": 2,
			 "bloodDemand": 28388
			},
			{
			 "time": 3,
			 "bloodDemand": 14588
			},
			{
			 "time": 4,
			 "bloodDemand": 6647
			},
			{
			 "time": 5,
			 "bloodDemand": 2273
			}
		 ]
		}
	 ]
	},
	{
	 "id": 192,
	 "Hospitals": [
		{
		 "id": 0,
		 "Periods": [
			{
			 "time": 1,
			 "bloodDemand": 16713
			},
			{
			 "time": 2,
			 "bloodDemand": 14335
			},
			{
			 "time": 3,
			 "bloodDemand": 12097
			},
			{
			 "time": 4,
			 "bloodDemand": 9406
			},
			{
			 "time": 5,
			 "bloodDemand": 9307
			}
		 ]
		}
	 ]
	},
	{
	 "id": 193,
	 "Hospitals": [
		{
		 "id": 0,
		 "Periods": [
			{
			 "time": 1,
			 "bloodDemand": 66291
			},
			{
			 "time": 2,
			 "bloodDemand": 23431
			},
			{
			 "time": 3,
			 "bloodDemand": 10138
			},
			{
			 "time": 4,
			 "bloodDemand": 3365
			},
			{
			 "time": 5,
			 "bloodDemand": 1627
			}
		 ]
		}
	 ]
	},
	{
	 "id": 194,
	 "Hospitals": [
		{
		 "id": 0,
		 "Periods": [
			{
			 "time": 1,
			 "bloodDemand": 94856
			},
			{
			 "time": 2,
			 "bloodDemand": 9621
			},
			{
			 "time": 3,
			 "bloodDemand": 1118
			},
			{
			 "time": 4,
			 "bloodDemand": 357
			},
			{
			 "time": 5,
			 "bloodDemand": 60
			}
		 ]
		}
	 ]
	},
	{
	 "id": 195,
	 "Hospitals": [
		{
		 "id": 0,
		 "Periods": [
			{
			 "time": 1,
			 "bloodDemand": 45912
			},
			{
			 "time": 2,
			 "bloodDemand": 23543
			},
			{
			 "time": 3,
			 "bloodDemand": 16323
			},
			{
			 "time": 4,
			 "bloodDemand": 8871
			},
			{
			 "time": 5,
			 "bloodDemand": 4887
			}
		 ]
		}
	 ]
	},
	{
	 "id": 196,
	 "Hospitals": [
		{
		 "id": 0,
		 "Periods": [
			{
			 "time": 1,
			 "bloodDemand": 60114
			},
			{
			 "time": 2,
			 "bloodDemand": 25947
			},
			{
			 "time": 3,
			 "bloodDemand": 11322
			},
			{
			 "time": 4,
			 "bloodDemand": 4593
			},
			{
			 "time": 5,
			 "bloodDemand": 2287
			}
		 ]
		}
	 ]
	},
	{
	 "id": 197,
	 "Hospitals": [
		{
		 "id": 0,
		 "Periods": [
			{
			 "time": 1,
			 "bloodDemand": 43127
			},
			{
			 "time": 2,
			 "bloodDemand": 24805
			},
			{
			 "time": 3,
			 "bloodDemand": 17072
			},
			{
			 "time": 4,
			 "bloodDemand": 6909
			},
			{
			 "time": 5,
			 "bloodDemand": 6336
			}
		 ]
		}
	 ]
	},
	{
	 "id": 198,
	 "Hospitals": [
		{
		 "id": 0,
		 "Periods": [
			{
			 "time": 1,
			 "bloodDemand": 76983
			},
			{
			 "time": 2,
			 "bloodDemand": 22314
			},
			{
			 "time": 3,
			 "bloodDemand": 4913
			},
			{
			 "time": 4,
			 "bloodDemand": 1228
			},
			{
			 "time": 5,
			 "bloodDemand": 466
			}
		 ]
		}
	 ]
	},
	{
	 "id": 199,
	 "Hospitals": [
		{
		 "id": 0,
		 "Periods": [
			{
			 "time": 1,
			 "bloodDemand": 52731
			},
			{
			 "time": 2,
			 "bloodDemand": 33170
			},
			{
			 "time": 3,
			 "bloodDemand": 10897
			},
			{
			 "time": 4,
			 "bloodDemand": 3990
			},
			{
			 "time": 5,
			 "bloodDemand": 3018
			}
		 ]
		}
	 ]
	}
 ]
}