{
 "NumberOfBudgetValues": 5,
 "NumberOfPenalityValues": 7,
 "BudgetUpperBound": 460445,
 "HigherBloodDemand": 220479,
 "Budgets": [
	{
	 "id": 0,
	 "value": 46044.5
	},
	{
	 "id": 1,
	 "value": 92089
	},
	{
	 "id": 2,
	 "value": 138134
	},
	{
	 "id": 3,
	 "value": 184178
	},
	{
	 "id": 4,
	 "value": 230223
	}
 ],
 "Penalities": [
	{
	 "id": 0,
	 "value": 2.09
	},
	{
	 "id": 1,
	 "value": 10.44
	},
	{
	 "id": 2,
	 "value": 20.88
	},
	{
	 "id": 3,
	 "value": 31.33
	},
	{
	 "id": 4,
	 "value": 52.21
	},
	{
	 "id": 5,
	 "value": 73.09
	},
	{
	 "id": 6,
	 "value": 93.98
	}
 ]
}