{
 "NumberOfBudgetValues": 5,
 "NumberOfPenalityValues": 7,
 "BudgetUpperBound": 116133,
 "HigherBloodDemand": 93743,
 "Budgets": [
	{
	 "id": 0,
	 "value": 11613.3
	},
	{
	 "id": 1,
	 "value": 23226.6
	},
	{
	 "id": 2,
	 "value": 34839.8
	},
	{
	 "id": 3,
	 "value": 46453.1
	},
	{
	 "id": 4,
	 "value": 58066.4
	}
 ],
 "Penalities": [
	{
	 "id": 0,
	 "value": 1.24
	},
	{
	 "id": 1,
	 "value": 6.19
	},
	{
	 "id": 2,
	 "value": 12.39
	},
	{
	 "id": 3,
	 "value": 18.58
	},
	{
	 "id": 4,
	 "value": 30.97
	},
	{
	 "id": 5,
	 "value": 43.36
	},
	{
	 "id": 6,
	 "value": 55.75
	}
 ]
}